ypy_sqlite/__init__.py
ypy_sqlite/persistence.py
ypy_sqlite/sqlite_adapter.py
ypy_sqlite/utils.py
ypy_sqlite/tests/__init__.py
ypy_sqlite/tests/test_persistence.py
ypy_sqlite-0.1.0.dist-info/METADATA
ypy_sqlite-0.1.0.dist-info/WHEEL
ypy_sqlite-0.1.0.dist-info/top_level.txt
ypy_sqlite-0.1.0.dist-info/RECORD
