Metadata-Version: 2.4
Name: ypy-sqlite
Version: 0.1.0
Summary: SQLite persistence provider for YPY (Python bindings for YJS)
Author-email: Viktor Nawrath <vima00@seznam.cz>
License-Expression: MIT
Project-URL: Homepage, https://github.com/vnawrath/ypy-sqlite
Project-URL: Repository, https://github.com/vnawrath/ypy-sqlite
Project-URL: Bug Tracker, https://github.com/vnawrath/ypy-sqlite/issues
Keywords: yjs,crdt,sqlite,persistence,collaboration,y-py
Classifier: Development Status :: 3 - Alpha
Classifier: Intended Audience :: Developers
Classifier: Programming Language :: Python :: 3
Classifier: Programming Language :: Python :: 3.7
Classifier: Programming Language :: Python :: 3.8
Classifier: Programming Language :: Python :: 3.9
Classifier: Programming Language :: Python :: 3.10
Classifier: Programming Language :: Python :: 3.11
Requires-Python: >=3.7
Requires-Dist: y-py>=0.6.2
Requires-Dist: aiosqlite>=0.18.0
